odoo/addons/l10n_it_dichiarazione_intento/README.rst
odoo/addons/l10n_it_dichiarazione_intento/__init__.py
odoo/addons/l10n_it_dichiarazione_intento/__manifest__.py
odoo/addons/l10n_it_dichiarazione_intento/data/sequence.xml
odoo/addons/l10n_it_dichiarazione_intento/i18n/it.po
odoo/addons/l10n_it_dichiarazione_intento/i18n/l10n_it_dichiarazione_intento.pot
odoo/addons/l10n_it_dichiarazione_intento/models/__init__.py
odoo/addons/l10n_it_dichiarazione_intento/models/account.py
odoo/addons/l10n_it_dichiarazione_intento/models/account_invoice.py
odoo/addons/l10n_it_dichiarazione_intento/models/company.py
odoo/addons/l10n_it_dichiarazione_intento/models/dichiarazione_intento.py
odoo/addons/l10n_it_dichiarazione_intento/models/product.py
odoo/addons/l10n_it_dichiarazione_intento/models/sale.py
odoo/addons/l10n_it_dichiarazione_intento/readme/CONFIGURE.rst
odoo/addons/l10n_it_dichiarazione_intento/readme/CONTRIBUTORS.rst
odoo/addons/l10n_it_dichiarazione_intento/readme/DESCRIPTION.rst
odoo/addons/l10n_it_dichiarazione_intento/readme/USAGE.rst
odoo/addons/l10n_it_dichiarazione_intento/security/declaration_security.xml
odoo/addons/l10n_it_dichiarazione_intento/security/ir.model.access.csv
odoo/addons/l10n_it_dichiarazione_intento/static/description/icon.png
odoo/addons/l10n_it_dichiarazione_intento/static/description/index.html
odoo/addons/l10n_it_dichiarazione_intento/tests/__init__.py
odoo/addons/l10n_it_dichiarazione_intento/tests/test_account.py
odoo/addons/l10n_it_dichiarazione_intento/tests/test_dichiarazione_intento.py
odoo/addons/l10n_it_dichiarazione_intento/views/account_invoice_view.xml
odoo/addons/l10n_it_dichiarazione_intento/views/account_view.xml
odoo/addons/l10n_it_dichiarazione_intento/views/company_view.xml
odoo/addons/l10n_it_dichiarazione_intento/views/dichiarazione_intento_view.xml
odoo/addons/l10n_it_dichiarazione_intento/wizard/__init__.py
odoo/addons/l10n_it_dichiarazione_intento/wizard/manually_declarations.py
odoo12_addon_l10n_it_dichiarazione_intento-12.0.0.2.1.dist-info/METADATA
odoo12_addon_l10n_it_dichiarazione_intento-12.0.0.2.1.dist-info/WHEEL
odoo12_addon_l10n_it_dichiarazione_intento-12.0.0.2.1.dist-info/top_level.txt
odoo12_addon_l10n_it_dichiarazione_intento-12.0.0.2.1.dist-info/RECORD
