Metadata-Version: 2.1
Name: odoo12-addon-l10n-it-dichiarazione-intento
Version: 12.0.0.2.1
Summary: Gestione dichiarazioni di intento
Home-page: https://github.com/OCA/l10n-italy/tree/12.0/l10n_it_dichiarazione_intento
Author: Francesco Apruzzese, Odoo Community Association (OCA), Sergio Corato, Glauco Prina, Lara Baggio
Author-email: support@odoo-community.org
License: AGPL-3
Platform: UNKNOWN
Classifier: Programming Language :: Python
Classifier: Framework :: Odoo
Classifier: Framework :: Odoo :: 12.0
Classifier: License :: OSI Approved :: GNU Affero General Public License v3
Requires-Python: >=3.5
Requires-Dist: odoo (<12.1dev,>=12.0a)
